ecdtools/__init__.py
ecdtools/ibis.py
ecdtools/version.py
ecdtools-0.4.0.dist-info/DESCRIPTION.rst
ecdtools-0.4.0.dist-info/METADATA
ecdtools-0.4.0.dist-info/RECORD
ecdtools-0.4.0.dist-info/WHEEL
ecdtools-0.4.0.dist-info/metadata.json
ecdtools-0.4.0.dist-info/top_level.txt
