Metadata-Version: 2.0
Name: ecdtools
Version: 0.4.0
Summary: Electronic circuit design tools.
Home-page: UNKNOWN
Author: Erik Moqvist
Author-email: erik.moqvist@gmail.com
License: MIT
Platform: UNKNOWN
Classifier: License :: OSI Approved :: MIT License
Classifier: Programming Language :: Python :: 3
Requires-Dist: textparser (>=0.18.0)
